DEODR-0.2.3.data/data/C++/DifferentiableRenderer.h
deodr/__init__.py
deodr/differentiable_renderer.py
deodr/differentiable_renderer_cython.cp311-win32.pyd
deodr/differentiable_renderer_cython.pyx
deodr/laplacian_rigid_energy.py
deodr/mesh_fitter.py
deodr/meshlab_io.py
deodr/obj.py
deodr/tools.py
deodr/triangulated_mesh.py
deodr/data/depth.bin
deodr/data/duck.obj
deodr/data/duck.obj.mtl
deodr/data/duck.png
deodr/data/duckResampled.obj
deodr/data/hand.obj
deodr/data/hand.png
deodr/data/trefle.jpg
deodr/data/cube/ir_cube.obj
deodr/data/cube/rgb_cube.ply
deodr/data/cube/textured_cube.obj.mtl
deodr/data/cube/textured_cube.png
deodr/data/hand_multiview/IMG-1842.jpg
deodr/data/hand_multiview/IMG-1843.jpg
deodr/data/hand_multiview/IMG-1844.jpg
deodr/data/test/duck.png
deodr/examples/__init__.py
deodr/examples/depth_image_hand_fitting.py
deodr/examples/eigen_faces.py
deodr/examples/mesh_viewer.py
deodr/examples/render_mesh.py
deodr/examples/rgb_image_hand_fitting.py
deodr/examples/rgb_multiview_hand.py
deodr/examples/triangle_soup_fitting.py
deodr/opengl/__init__.py
deodr/opengl/moderngl.py
deodr/opengl/pyrender.py
deodr/opengl/shaders.py
deodr/pytorch/__init__.py
deodr/pytorch/differentiable_renderer_pytorch.py
deodr/pytorch/laplacian_rigid_energy_pytorch.py
deodr/pytorch/mesh_fitter_pytorch.py
deodr/pytorch/triangulated_mesh_pytorch.py
deodr/tensorflow/__init__.py
deodr/tensorflow/differentiable_renderer_tensorflow.py
deodr/tensorflow/laplacian_rigid_energy_tensorflow.py
deodr/tensorflow/mesh_fitter_tensorflow.py
deodr/tensorflow/tools.py
deodr/tensorflow/triangulated_mesh_tensorflow.py
DEODR-0.2.3.dist-info/LICENSE
DEODR-0.2.3.dist-info/METADATA
DEODR-0.2.3.dist-info/WHEEL
DEODR-0.2.3.dist-info/top_level.txt
DEODR-0.2.3.dist-info/RECORD
