Metadata-Version: 2.1
Name: DEODR
Version: 0.2.3
Summary: A differentiable 3D mesh renderer
Home-page: https://github.com/martinResearch/DEODR
Author-email: Martin de La Gorce <martin.delgorce@gmail.com>
License: BSD
Requires-Python: >=3.9
License-File: LICENSE
Requires-Dist: numpy>=2.0.0
Requires-Dist: scipy
